{
	"parent": "minecraft:recipes/root",
	"rewards": {
		"recipes": [
			"mubble:crafting/timeswap_table"
		]
	},
	"criteria": {
		"has_clock": {
			"trigger": "minecraft:inventory_changed",
			"conditions": {
				"items": [
					{
						"item": "minecraft:clock"
					}
				]
			}
		},
		"has_vanadium": {
			"trigger": "minecraft:inventory_changed",
			"conditions": {
				"items": [
					{
						"item": "mubble:vanadium"
					}
				]
			}
		},
		"has_the_recipe": {
			"trigger": "minecraft:recipe_unlocked",
			"conditions": {
				"recipe": "mubble:crafting/timeswap_table"
			}
		}
	},
	"requirements": [
		[
			"has_clock",
			"has_vanadium",
			"has_the_recipe"
		]
	]
}