{
	"variants":
	{
		"":
		[
			{"model": "mubble:block/cyan_bricks/0"},
			{"model": "mubble:block/cyan_bricks/1"},
			{"model": "mubble:block/cyan_bricks/2"},
			{"model": "mubble:block/cyan_bricks/3"},
			{"model": "mubble:block/cyan_bricks/4"},
			{"model": "mubble:block/cyan_bricks/12"},
			{"model": "mubble:block/cyan_bricks/13"},
			{"model": "mubble:block/cyan_bricks/14"},
			{"model": "mubble:block/cyan_bricks/23"},
			{"model": "mubble:block/cyan_bricks/24"},
			{"model": "mubble:block/cyan_bricks/34"},
			{"model": "mubble:block/cyan_bricks/123"},
			{"model": "mubble:block/cyan_bricks/124"},
			{"model": "mubble:block/cyan_bricks/134"},
			{"model": "mubble:block/cyan_bricks/234"},
			{"model": "mubble:block/cyan_bricks/1234"}
		]
	}
}